setup.py
internet_calendar/__init__.py
internet_calendar.egg-info/PKG-INFO
internet_calendar.egg-info/SOURCES.txt
internet_calendar.egg-info/dependency_links.txt
internet_calendar.egg-info/requires.txt
internet_calendar.egg-info/top_level.txt