Metadata-Version: 1.0
Name: internet-calendar
Version: 0.1.1
Summary: unofficial api for https://forekast.com/
Home-page: UNKNOWN
Author: jarbasAI
Author-email: jarbasai@mailfence.com
License: MIT
Platform: UNKNOWN
